[{"name":"C:\\Users\\Exist\\AppData\\Local\\citizenfx\\sdk-storage\\system-resources\\resources\\[gameplay]\\chat\\html\\index.html","stats":{"mtime":1691353425193.3164,"size":391,"inode":844424930895598}},{"name":"C:\\Users\\Exist\\AppData\\Local\\citizenfx\\sdk-storage\\system-resources\\resources\\[gameplay]\\chat\\node_modules\\lodash\\lodash.js","stats":{"mtime":1691353621320,"size":540512,"inode":562949954303353}},{"name":"C:\\Users\\Exist\\AppData\\Local\\citizenfx\\sdk-storage\\system-resources\\resources\\[system]\\[builders]\\webpack\\node_modules\\webpack\\buildin\\global.js","stats":{"mtime":1691353616260,"size":472,"inode":844424930981325}},{"name":"C:\\Users\\Exist\\AppData\\Local\\citizenfx\\sdk-storage\\system-resources\\resources\\[system]\\[builders]\\webpack\\node_modules\\webpack\\buildin\\module.js","stats":{"mtime":1691353616260,"size":497,"inode":844424930981329}},{"name":"C:\\Users\\Exist\\AppData\\Local\\citizenfx\\sdk-storage\\system-resources\\resources\\[gameplay]\\chat\\html\\App.ts","stats":{"mtime":1691353425191.8118,"size":13445,"inode":844424930895586}},{"name":"C:\\Users\\Exist\\AppData\\Local\\citizenfx\\sdk-storage\\system-resources\\resources\\[gameplay]\\chat\\html\\App.vue","stats":{"mtime":1691353425191.8118,"size":1544,"inode":844424930895591}},{"name":"C:\\Users\\Exist\\AppData\\Local\\citizenfx\\sdk-storage\\system-resources\\resources\\[gameplay]\\chat\\html\\Message.ts","stats":{"mtime":1691353425191.8118,"size":3273,"inode":844424930895592}},{"name":"C:\\Users\\Exist\\AppData\\Local\\citizenfx\\sdk-storage\\system-resources\\resources\\[gameplay]\\chat\\html\\Message.vue","stats":{"mtime":1691353425191.8118,"size":167,"inode":844424930895589}},{"name":"C:\\Users\\Exist\\AppData\\Local\\citizenfx\\sdk-storage\\system-resources\\resources\\[gameplay]\\chat\\html\\Suggestions.ts","stats":{"mtime":1691353425193.3164,"size":1696,"inode":844424930895594}},{"name":"C:\\Users\\Exist\\AppData\\Local\\citizenfx\\sdk-storage\\system-resources\\resources\\[gameplay]\\chat\\html\\Suggestions.vue","stats":{"mtime":1691353425193.3164,"size":909,"inode":844424930895593}},{"name":"C:\\Users\\Exist\\AppData\\Local\\citizenfx\\sdk-storage\\system-resources\\resources\\[gameplay]\\chat\\html\\config.ts","stats":{"mtime":1691353425193.3164,"size":479,"inode":844424930895595}},{"name":"C:\\Users\\Exist\\AppData\\Local\\citizenfx\\sdk-storage\\system-resources\\resources\\[gameplay]\\chat\\html\\index.d.ts","stats":{"mtime":1691353425193.3164,"size":75,"inode":844424930895596}},{"name":"C:\\Users\\Exist\\AppData\\Local\\citizenfx\\sdk-storage\\system-resources\\resources\\[gameplay]\\chat\\html\\index.html","stats":{"mtime":1691353425193.3164,"size":391,"inode":844424930895598}},{"name":"C:\\Users\\Exist\\AppData\\Local\\citizenfx\\sdk-storage\\system-resources\\resources\\[gameplay]\\chat\\html\\main.ts","stats":{"mtime":1691353425193.3164,"size":124,"inode":844424930895600}},{"name":"C:\\Users\\Exist\\AppData\\Local\\citizenfx\\sdk-storage\\system-resources\\resources\\[gameplay]\\chat\\html\\utils.ts","stats":{"mtime":1691353425193.3164,"size":685,"inode":844424930895604}},{"name":"C:\\Users\\Exist\\AppData\\Local\\citizenfx\\sdk-storage\\system-resources\\resources\\[gameplay]\\chat\\node_modules\\@types\\events\\index.d.ts","stats":{"mtime":1691353624667,"size":1273,"inode":562949954302027}},{"name":"C:\\Users\\Exist\\AppData\\Local\\citizenfx\\sdk-storage\\system-resources\\resources\\[gameplay]\\chat\\node_modules\\@types\\glob\\index.d.ts","stats":{"mtime":1691353624141,"size":3053,"inode":562949954302039}},{"name":"C:\\Users\\Exist\\AppData\\Local\\citizenfx\\sdk-storage\\system-resources\\resources\\[gameplay]\\chat\\node_modules\\@types\\minimatch\\index.d.ts","stats":{"mtime":1691353624670,"size":5588,"inode":562949954302094}},{"name":"C:\\Users\\Exist\\AppData\\Local\\citizenfx\\sdk-storage\\system-resources\\resources\\[gameplay]\\chat\\node_modules\\@types\\node\\assert.d.ts","stats":{"mtime":1691353624684,"size":2910,"inode":562949954302043}},{"name":"C:\\Users\\Exist\\AppData\\Local\\citizenfx\\sdk-storage\\system-resources\\resources\\[gameplay]\\chat\\node_modules\\@types\\node\\async_hooks.d.ts","stats":{"mtime":1691353624684,"size":10846,"inode":562949954302045}},{"name":"C:\\Users\\Exist\\AppData\\Local\\citizenfx\\sdk-storage\\system-resources\\resources\\[gameplay]\\chat\\node_modules\\@types\\node\\base.d.ts","stats":{"mtime":1691353624684,"size":1588,"inode":562949954302046}},{"name":"C:\\Users\\Exist\\AppData\\Local\\citizenfx\\sdk-storage\\system-resources\\resources\\[gameplay]\\chat\\node_modules\\@types\\node\\buffer.d.ts","stats":{"mtime":1691353624684,"size":706,"inode":562949954302047}},{"name":"C:\\Users\\Exist\\AppData\\Local\\citizenfx\\sdk-storage\\system-resources\\resources\\[gameplay]\\chat\\node_modules\\@types\\node\\child_process.d.ts","stats":{"mtime":1691353624684,"size":24552,"inode":562949954302048}},{"name":"C:\\Users\\Exist\\AppData\\Local\\citizenfx\\sdk-storage\\system-resources\\resources\\[gameplay]\\chat\\node_modules\\@types\\node\\cluster.d.ts","stats":{"mtime":1691353624684,"size":16197,"inode":562949954302052}},{"name":"C:\\Users\\Exist\\AppData\\Local\\citizenfx\\sdk-storage\\system-resources\\resources\\[gameplay]\\chat\\node_modules\\@types\\node\\console.d.ts","stats":{"mtime":1691353624684,"size":51,"inode":562949954302051}},{"name":"C:\\Users\\Exist\\AppData\\Local\\citizenfx\\sdk-storage\\system-resources\\resources\\[gameplay]\\chat\\node_modules\\@types\\node\\constants.d.ts","stats":{"mtime":1691353624684,"size":459,"inode":562949954302050}},{"name":"C:\\Users\\Exist\\AppData\\Local\\citizenfx\\sdk-storage\\system-resources\\resources\\[gameplay]\\chat\\node_modules\\@types\\node\\crypto.d.ts","stats":{"mtime":1691353624684,"size":30570,"inode":562949954302049}},{"name":"C:\\Users\\Exist\\AppData\\Local\\citizenfx\\sdk-storage\\system-resources\\resources\\[gameplay]\\chat\\node_modules\\@types\\node\\dgram.d.ts","stats":{"mtime":1691353624684,"size":7156,"inode":562949954302054}},{"name":"C:\\Users\\Exist\\AppData\\Local\\citizenfx\\sdk-storage\\system-resources\\resources\\[gameplay]\\chat\\node_modules\\@types\\node\\dns.d.ts","stats":{"mtime":1691353624684,"size":16002,"inode":562949954302056}},{"name":"C:\\Users\\Exist\\AppData\\Local\\citizenfx\\sdk-storage\\system-resources\\resources\\[gameplay]\\chat\\node_modules\\@types\\node\\domain.d.ts","stats":{"mtime":1691353624684,"size":545,"inode":562949954302053}},{"name":"C:\\Users\\Exist\\AppData\\Local\\citizenfx\\sdk-storage\\system-resources\\resources\\[gameplay]\\chat\\node_modules\\@types\\node\\events.d.ts","stats":{"mtime":1691353624684,"size":1841,"inode":562949954302057}},{"name":"C:\\Users\\Exist\\AppData\\Local\\citizenfx\\sdk-storage\\system-resources\\resources\\[gameplay]\\chat\\node_modules\\@types\\node\\fs.d.ts","stats":{"mtime":1691353624684,"size":140811,"inode":562949954302055}},{"name":"C:\\Users\\Exist\\AppData\\Local\\citizenfx\\sdk-storage\\system-resources\\resources\\[gameplay]\\chat\\node_modules\\@types\\node\\globals.d.ts","stats":{"mtime":1691353624684,"size":45295,"inode":562949954302058}},{"name":"C:\\Users\\Exist\\AppData\\Local\\citizenfx\\sdk-storage\\system-resources\\resources\\[gameplay]\\chat\\node_modules\\@types\\node\\http.d.ts","stats":{"mtime":1691353624684,"size":17738,"inode":562949954302059}},{"name":"C:\\Users\\Exist\\AppData\\Local\\citizenfx\\sdk-storage\\system-resources\\resources\\[gameplay]\\chat\\node_modules\\@types\\node\\http2.d.ts","stats":{"mtime":1691353624684,"size":56307,"inode":562949954302060}},{"name":"C:\\Users\\Exist\\AppData\\Local\\citizenfx\\sdk-storage\\system-resources\\resources\\[gameplay]\\chat\\node_modules\\@types\\node\\https.d.ts","stats":{"mtime":1691353624684,"size":1684,"inode":562949954302062}},{"name":"C:\\Users\\Exist\\AppData\\Local\\citizenfx\\sdk-storage\\system-resources\\resources\\[gameplay]\\chat\\node_modules\\@types\\node\\inspector.d.ts","stats":{"mtime":1691353624684,"size":121692,"inode":562949954302064}},{"name":"C:\\Users\\Exist\\AppData\\Local\\citizenfx\\sdk-storage\\system-resources\\resources\\[gameplay]\\chat\\node_modules\\@types\\node\\module.d.ts","stats":{"mtime":1691353624684,"size":1741,"inode":562949954302070}},{"name":"C:\\Users\\Exist\\AppData\\Local\\citizenfx\\sdk-storage\\system-resources\\resources\\[gameplay]\\chat\\node_modules\\@types\\node\\net.d.ts","stats":{"mtime":1691353624684,"size":12804,"inode":562949954302066}},{"name":"C:\\Users\\Exist\\AppData\\Local\\citizenfx\\sdk-storage\\system-resources\\resources\\[gameplay]\\chat\\node_modules\\@types\\node\\os.d.ts","stats":{"mtime":1691353624684,"size":8178,"inode":562949954302065}},{"name":"C:\\Users\\Exist\\AppData\\Local\\citizenfx\\sdk-storage\\system-resources\\resources\\[gameplay]\\chat\\node_modules\\@types\\node\\path.d.ts","stats":{"mtime":1691353624684,"size":6309,"inode":562949954302067}},{"name":"C:\\Users\\Exist\\AppData\\Local\\citizenfx\\sdk-storage\\system-resources\\resources\\[gameplay]\\chat\\node_modules\\@types\\node\\perf_hooks.d.ts","stats":{"mtime":1691353624684,"size":12044,"inode":562949954302069}},{"name":"C:\\Users\\Exist\\AppData\\Local\\citizenfx\\sdk-storage\\system-resources\\resources\\[gameplay]\\chat\\node_modules\\@types\\node\\process.d.ts","stats":{"mtime":1691353624684,"size":517,"inode":562949954302071}},{"name":"C:\\Users\\Exist\\AppData\\Local\\citizenfx\\sdk-storage\\system-resources\\resources\\[gameplay]\\chat\\node_modules\\@types\\node\\punycode.d.ts","stats":{"mtime":1691353624684,"size":378,"inode":562949954302072}},{"name":"C:\\Users\\Exist\\AppData\\Local\\citizenfx\\sdk-storage\\system-resources\\resources\\[gameplay]\\chat\\node_modules\\@types\\node\\querystring.d.ts","stats":{"mtime":1691353624684,"size":1017,"inode":562949954302073}},{"name":"C:\\Users\\Exist\\AppData\\Local\\citizenfx\\sdk-storage\\system-resources\\resources\\[gameplay]\\chat\\node_modules\\@types\\node\\readline.d.ts","stats":{"mtime":1691353624684,"size":7330,"inode":562949954302074}},{"name":"C:\\Users\\Exist\\AppData\\Local\\citizenfx\\sdk-storage\\system-resources\\resources\\[gameplay]\\chat\\node_modules\\@types\\node\\repl.d.ts","stats":{"mtime":1691353624684,"size":17874,"inode":562949954302075}},{"name":"C:\\Users\\Exist\\AppData\\Local\\citizenfx\\sdk-storage\\system-resources\\resources\\[gameplay]\\chat\\node_modules\\@types\\node\\stream.d.ts","stats":{"mtime":1691353624684,"size":18986,"inode":562949954302077}},{"name":"C:\\Users\\Exist\\AppData\\Local\\citizenfx\\sdk-storage\\system-resources\\resources\\[gameplay]\\chat\\node_modules\\@types\\node\\string_decoder.d.ts","stats":{"mtime":1691353624684,"size":185,"inode":562949954302078}},{"name":"C:\\Users\\Exist\\AppData\\Local\\citizenfx\\sdk-storage\\system-resources\\resources\\[gameplay]\\chat\\node_modules\\@types\\node\\timers.d.ts","stats":{"mtime":1691353624684,"size":826,"inode":562949954302080}},{"name":"C:\\Users\\Exist\\AppData\\Local\\citizenfx\\sdk-storage\\system-resources\\resources\\[gameplay]\\chat\\node_modules\\@types\\node\\tls.d.ts","stats":{"mtime":1691353624684,"size":37312,"inode":562949954302079}},{"name":"C:\\Users\\Exist\\AppData\\Local\\citizenfx\\sdk-storage\\system-resources\\resources\\[gameplay]\\chat\\node_modules\\@types\\node\\trace_events.d.ts","stats":{"mtime":1691353624684,"size":2113,"inode":562949954302081}},{"name":"C:\\Users\\Exist\\AppData\\Local\\citizenfx\\sdk-storage\\system-resources\\resources\\[gameplay]\\chat\\node_modules\\@types\\node\\ts3.2\\fs.d.ts","stats":{"mtime":1691353624684,"size":1088,"inode":562949954305843}},{"name":"C:\\Users\\Exist\\AppData\\Local\\citizenfx\\sdk-storage\\system-resources\\resources\\[gameplay]\\chat\\node_modules\\@types\\node\\ts3.2\\globals.d.ts","stats":{"mtime":1691353624684,"size":640,"inode":562949954305839}},{"name":"C:\\Users\\Exist\\AppData\\Local\\citizenfx\\sdk-storage\\system-resources\\resources\\[gameplay]\\chat\\node_modules\\@types\\node\\ts3.2\\index.d.ts","stats":{"mtime":1691353624684,"size":591,"inode":562949954305845}},{"name":"C:\\Users\\Exist\\AppData\\Local\\citizenfx\\sdk-storage\\system-resources\\resources\\[gameplay]\\chat\\node_modules\\@types\\node\\ts3.2\\util.d.ts","stats":{"mtime":1691353624684,"size":280,"inode":562949954305842}},{"name":"C:\\Users\\Exist\\AppData\\Local\\citizenfx\\sdk-storage\\system-resources\\resources\\[gameplay]\\chat\\node_modules\\@types\\node\\tty.d.ts","stats":{"mtime":1691353624684,"size":2442,"inode":562949954302083}},{"name":"C:\\Users\\Exist\\AppData\\Local\\citizenfx\\sdk-storage\\system-resources\\resources\\[gameplay]\\chat\\node_modules\\@types\\node\\url.d.ts","stats":{"mtime":1691353624684,"size":3828,"inode":562949954302082}},{"name":"C:\\Users\\Exist\\AppData\\Local\\citizenfx\\sdk-storage\\system-resources\\resources\\[gameplay]\\chat\\node_modules\\@types\\node\\util.d.ts","stats":{"mtime":1691353624684,"size":12173,"inode":562949954302085}},{"name":"C:\\Users\\Exist\\AppData\\Local\\citizenfx\\sdk-storage\\system-resources\\resources\\[gameplay]\\chat\\node_modules\\@types\\node\\v8.d.ts","stats":{"mtime":1691353624684,"size":6769,"inode":562949954302086}},{"name":"C:\\Users\\Exist\\AppData\\Local\\citizenfx\\sdk-storage\\system-resources\\resources\\[gameplay]\\chat\\node_modules\\@types\\node\\vm.d.ts","stats":{"mtime":1691353624684,"size":5730,"inode":562949954302084}},{"name":"C:\\Users\\Exist\\AppData\\Local\\citizenfx\\sdk-storage\\system-resources\\resources\\[gameplay]\\chat\\node_modules\\@types\\node\\worker_threads.d.ts","stats":{"mtime":1691353624684,"size":8461,"inode":562949954302087}},{"name":"C:\\Users\\Exist\\AppData\\Local\\citizenfx\\sdk-storage\\system-resources\\resources\\[gameplay]\\chat\\node_modules\\@types\\node\\zlib.d.ts","stats":{"mtime":1691353624684,"size":12182,"inode":562949954302089}},{"name":"C:\\Users\\Exist\\AppData\\Local\\citizenfx\\sdk-storage\\system-resources\\resources\\[gameplay]\\chat\\node_modules\\lodash\\lodash.js","stats":{"mtime":1691353621320,"size":540512,"inode":562949954303353}},{"name":"C:\\Users\\Exist\\AppData\\Local\\citizenfx\\sdk-storage\\system-resources\\resources\\[gameplay]\\chat\\node_modules\\typescript\\lib\\lib.dom.d.ts","stats":{"mtime":1691353622081,"size":840098,"inode":562949954307922}},{"name":"C:\\Users\\Exist\\AppData\\Local\\citizenfx\\sdk-storage\\system-resources\\resources\\[gameplay]\\chat\\node_modules\\typescript\\lib\\lib.es2015.collection.d.ts","stats":{"mtime":1691353622081,"size":2910,"inode":562949954307924}},{"name":"C:\\Users\\Exist\\AppData\\Local\\citizenfx\\sdk-storage\\system-resources\\resources\\[gameplay]\\chat\\node_modules\\typescript\\lib\\lib.es2015.core.d.ts","stats":{"mtime":1691353622081,"size":20397,"inode":562949954307925}},{"name":"C:\\Users\\Exist\\AppData\\Local\\citizenfx\\sdk-storage\\system-resources\\resources\\[gameplay]\\chat\\node_modules\\typescript\\lib\\lib.es2015.d.ts","stats":{"mtime":1691353622081,"size":1261,"inode":562949954307923}},{"name":"C:\\Users\\Exist\\AppData\\Local\\citizenfx\\sdk-storage\\system-resources\\resources\\[gameplay]\\chat\\node_modules\\typescript\\lib\\lib.es2015.generator.d.ts","stats":{"mtime":1691353622081,"size":2621,"inode":562949954307927}},{"name":"C:\\Users\\Exist\\AppData\\Local\\citizenfx\\sdk-storage\\system-resources\\resources\\[gameplay]\\chat\\node_modules\\typescript\\lib\\lib.es2015.iterable.d.ts","stats":{"mtime":1691353622081,"size":15415,"inode":562949954307926}},{"name":"C:\\Users\\Exist\\AppData\\Local\\citizenfx\\sdk-storage\\system-resources\\resources\\[gameplay]\\chat\\node_modules\\typescript\\lib\\lib.es2015.promise.d.ts","stats":{"mtime":1691353622081,"size":7362,"inode":562949954307928}},{"name":"C:\\Users\\Exist\\AppData\\Local\\citizenfx\\sdk-storage\\system-resources\\resources\\[gameplay]\\chat\\node_modules\\typescript\\lib\\lib.es2015.proxy.d.ts","stats":{"mtime":1691353622081,"size":1984,"inode":562949954307929}},{"name":"C:\\Users\\Exist\\AppData\\Local\\citizenfx\\sdk-storage\\system-resources\\resources\\[gameplay]\\chat\\node_modules\\typescript\\lib\\lib.es2015.reflect.d.ts","stats":{"mtime":1691353622081,"size":1929,"inode":562949954307930}},{"name":"C:\\Users\\Exist\\AppData\\Local\\citizenfx\\sdk-storage\\system-resources\\resources\\[gameplay]\\chat\\node_modules\\typescript\\lib\\lib.es2015.symbol.d.ts","stats":{"mtime":1691353622081,"size":1685,"inode":562949954307932}},{"name":"C:\\Users\\Exist\\AppData\\Local\\citizenfx\\sdk-storage\\system-resources\\resources\\[gameplay]\\chat\\node_modules\\typescript\\lib\\lib.es2015.symbol.wellknown.d.ts","stats":{"mtime":1691353622081,"size":10555,"inode":562949954307931}},{"name":"C:\\Users\\Exist\\AppData\\Local\\citizenfx\\sdk-storage\\system-resources\\resources\\[gameplay]\\chat\\node_modules\\typescript\\lib\\lib.es2016.array.include.d.ts","stats":{"mtime":1691353622081,"size":4968,"inode":562949954307933}},{"name":"C:\\Users\\Exist\\AppData\\Local\\citizenfx\\sdk-storage\\system-resources\\resources\\[gameplay]\\chat\\node_modules\\typescript\\lib\\lib.es2016.d.ts","stats":{"mtime":1691353622081,"size":939,"inode":562949954307934}},{"name":"C:\\Users\\Exist\\AppData\\Local\\citizenfx\\sdk-storage\\system-resources\\resources\\[gameplay]\\chat\\node_modules\\typescript\\lib\\lib.es2017.d.ts","stats":{"mtime":1691353622081,"size":1099,"inode":562949954307936}},{"name":"C:\\Users\\Exist\\AppData\\Local\\citizenfx\\sdk-storage\\system-resources\\resources\\[gameplay]\\chat\\node_modules\\typescript\\lib\\lib.es2017.intl.d.ts","stats":{"mtime":1691353622081,"size":1266,"inode":562949954307938}},{"name":"C:\\Users\\Exist\\AppData\\Local\\citizenfx\\sdk-storage\\system-resources\\resources\\[gameplay]\\chat\\node_modules\\typescript\\lib\\lib.es2017.object.d.ts","stats":{"mtime":1691353622081,"size":2492,"inode":562949954307940}},{"name":"C:\\Users\\Exist\\AppData\\Local\\citizenfx\\sdk-storage\\system-resources\\resources\\[gameplay]\\chat\\node_modules\\typescript\\lib\\lib.es2017.sharedmemory.d.ts","stats":{"mtime":1691353622081,"size":6270,"inode":562949954307939}},{"name":"C:\\Users\\Exist\\AppData\\Local\\citizenfx\\sdk-storage\\system-resources\\resources\\[gameplay]\\chat\\node_modules\\typescript\\lib\\lib.es2017.string.d.ts","stats":{"mtime":1691353622081,"size":2415,"inode":562949954307944}},{"name":"C:\\Users\\Exist\\AppData\\Local\\citizenfx\\sdk-storage\\system-resources\\resources\\[gameplay]\\chat\\node_modules\\typescript\\lib\\lib.es2017.typedarrays.d.ts","stats":{"mtime":1691353622081,"size":1470,"inode":562949954307942}},{"name":"C:\\Users\\Exist\\AppData\\Local\\citizenfx\\sdk-storage\\system-resources\\resources\\[gameplay]\\chat\\node_modules\\typescript\\lib\\lib.es2018.asyncgenerator.d.ts","stats":{"mtime":1691353622081,"size":2756,"inode":562949954307941}},{"name":"C:\\Users\\Exist\\AppData\\Local\\citizenfx\\sdk-storage\\system-resources\\resources\\[gameplay]\\chat\\node_modules\\typescript\\lib\\lib.es2018.asynciterable.d.ts","stats":{"mtime":1691353622081,"size":1780,"inode":562949954307943}},{"name":"C:\\Users\\Exist\\AppData\\Local\\citizenfx\\sdk-storage\\system-resources\\resources\\[gameplay]\\chat\\node_modules\\typescript\\lib\\lib.es2018.d.ts","stats":{"mtime":1691353622081,"size":1104,"inode":562949954307945}},{"name":"C:\\Users\\Exist\\AppData\\Local\\citizenfx\\sdk-storage\\system-resources\\resources\\[gameplay]\\chat\\node_modules\\typescript\\lib\\lib.es2018.intl.d.ts","stats":{"mtime":1691353622081,"size":1853,"inode":562949954307946}},{"name":"C:\\Users\\Exist\\AppData\\Local\\citizenfx\\sdk-storage\\system-resources\\resources\\[gameplay]\\chat\\node_modules\\typescript\\lib\\lib.es2018.promise.d.ts","stats":{"mtime":1691353622081,"size":1374,"inode":562949954307948}},{"name":"C:\\Users\\Exist\\AppData\\Local\\citizenfx\\sdk-storage\\system-resources\\resources\\[gameplay]\\chat\\node_modules\\typescript\\lib\\lib.es2018.regexp.d.ts","stats":{"mtime":1691353622081,"size":1255,"inode":562949954307949}},{"name":"C:\\Users\\Exist\\AppData\\Local\\citizenfx\\sdk-storage\\system-resources\\resources\\[gameplay]\\chat\\node_modules\\typescript\\lib\\lib.es2020.bigint.d.ts","stats":{"mtime":1691353622081,"size":31017,"inode":562949954307959}},{"name":"C:\\Users\\Exist\\AppData\\Local\\citizenfx\\sdk-storage\\system-resources\\resources\\[gameplay]\\chat\\node_modules\\typescript\\lib\\lib.es5.d.ts","stats":{"mtime":1691353622081,"size":208502,"inode":562949954307962}},{"name":"C:\\Users\\Exist\\AppData\\Local\\citizenfx\\sdk-storage\\system-resources\\resources\\[gameplay]\\chat\\node_modules\\typescript\\lib\\lib.esnext.intl.d.ts","stats":{"mtime":1691353622081,"size":1266,"inode":562949954307969}},{"name":"C:\\Users\\Exist\\AppData\\Local\\citizenfx\\sdk-storage\\system-resources\\resources\\[gameplay]\\chat\\node_modules\\vue-loader\\lib\\runtime\\componentNormalizer.js","stats":{"mtime":1691353622098,"size":2690,"inode":562949954309166}},{"name":"C:\\Users\\Exist\\AppData\\Local\\citizenfx\\sdk-storage\\system-resources\\resources\\[gameplay]\\chat\\node_modules\\vue\\dist\\vue.runtime.esm.js","stats":{"mtime":1691353620640,"size":227323,"inode":562949954308072}},{"name":"C:\\Users\\Exist\\AppData\\Local\\citizenfx\\sdk-storage\\system-resources\\resources\\[gameplay]\\chat\\node_modules\\vue\\types\\index.d.ts","stats":{"mtime":1691353620640,"size":600,"inode":562949954308077}},{"name":"C:\\Users\\Exist\\AppData\\Local\\citizenfx\\sdk-storage\\system-resources\\resources\\[gameplay]\\chat\\node_modules\\vue\\types\\options.d.ts","stats":{"mtime":1691353620640,"size":6992,"inode":562949954308079}},{"name":"C:\\Users\\Exist\\AppData\\Local\\citizenfx\\sdk-storage\\system-resources\\resources\\[gameplay]\\chat\\node_modules\\vue\\types\\plugin.d.ts","stats":{"mtime":1691353620640,"size":201,"inode":562949954308080}},{"name":"C:\\Users\\Exist\\AppData\\Local\\citizenfx\\sdk-storage\\system-resources\\resources\\[gameplay]\\chat\\node_modules\\vue\\types\\umd.d.ts","stats":{"mtime":1691353620640,"size":2154,"inode":562949954308081}},{"name":"C:\\Users\\Exist\\AppData\\Local\\citizenfx\\sdk-storage\\system-resources\\resources\\[gameplay]\\chat\\node_modules\\vue\\types\\vnode.d.ts","stats":{"mtime":1691353620640,"size":2111,"inode":562949954308082}},{"name":"C:\\Users\\Exist\\AppData\\Local\\citizenfx\\sdk-storage\\system-resources\\resources\\[gameplay]\\chat\\node_modules\\vue\\types\\vue.d.ts","stats":{"mtime":1691353620640,"size":6619,"inode":562949954308084}},{"name":"C:\\Users\\Exist\\AppData\\Local\\citizenfx\\sdk-storage\\system-resources\\resources\\[system]\\[builders]\\webpack\\node_modules\\process\\browser.js","stats":{"mtime":1691353617402,"size":5418,"inode":844424930979680}},{"name":"C:\\Users\\Exist\\AppData\\Local\\citizenfx\\sdk-storage\\system-resources\\resources\\[system]\\[builders]\\webpack\\node_modules\\setimmediate\\setImmediate.js","stats":{"mtime":1691353618017,"size":6475,"inode":844424930980037}},{"name":"C:\\Users\\Exist\\AppData\\Local\\citizenfx\\sdk-storage\\system-resources\\resources\\[system]\\[builders]\\webpack\\node_modules\\timers-browserify\\main.js","stats":{"mtime":1691353617445,"size":2022,"inode":844424930980182}},{"name":"C:\\Users\\Exist\\AppData\\Local\\citizenfx\\sdk-storage\\system-resources\\resources\\[system]\\[builders]\\webpack\\node_modules\\webpack\\buildin\\global.js","stats":{"mtime":1691353616260,"size":472,"inode":844424930981325}},{"name":"C:\\Users\\Exist\\AppData\\Local\\citizenfx\\sdk-storage\\system-resources\\resources\\[system]\\[builders]\\webpack\\node_modules\\webpack\\buildin\\module.js","stats":{"mtime":1691353616260,"size":497,"inode":844424930981329}}]